{
  "main": {
    "id": "b84b229081070cef",
    "type": "split",
    "children": [
      {
        "id": "38706fb5d59d637f",
        "type": "tabs",
        "children": [
          {
            "id": "077b52c4fe8e8b41",
            "type": "leaf",
            "state": {
              "type": "markdown",
              "state": {
                "file": "docs/LEGACY_LOG.md",
                "mode": "source",
                "source": false
              },
              "icon": "lucide-file",
              "title": "LEGACY_LOG"
            }
          }
        ]
      }
    ],
    "direction": "vertical"
  },
  "left": {
    "id": "4d3b4842be3f7c07",
    "type": "split",
    "children": [
      {
        "id": "91746a6a3e130ae8",
        "type": "tabs",
        "children": [
          {
            "id": "b11e791a2486de83",
            "type": "leaf",
            "state": {
              "type": "file-explorer",
              "state": {
                "sortOrder": "alphabetical",
                "autoReveal": false
              },
              "icon": "lucide-folder-closed",
              "title": "ファイルエクスプローラ"
            }
          },
          {
            "id": "d70a6fe96b3d6603",
            "type": "leaf",
            "state": {
              "type": "search",
              "state": {
                "query": "",
                "matchingCase": false,
                "explainSearch": false,
                "collapseAll": false,
                "extraContext": false,
                "sortOrder": "alphabetical"
              },
              "icon": "lucide-search",
              "title": "検索"
            }
          },
          {
            "id": "a82f09d8f2b3296d",
            "type": "leaf",
            "state": {
              "type": "bookmarks",
              "state": {},
              "icon": "lucide-bookmark",
              "title": "ブックマーク"
            }
          }
        ]
      }
    ],
    "direction": "horizontal",
    "width": 300
  },
  "right": {
    "id": "94a659905e7cf42b",
    "type": "split",
    "children": [
      {
        "id": "c83ae616420cb4bb",
        "type": "tabs",
        "children": [
          {
            "id": "4db08c80b4195ac6",
            "type": "leaf",
            "state": {
              "type": "backlink",
              "state": {
                "file": "docs/LEGACY_LOG.md",
                "collapseAll": false,
                "extraContext": false,
                "sortOrder": "alphabetical",
                "showSearch": false,
                "searchQuery": "",
                "backlinkCollapsed": false,
                "unlinkedCollapsed": true
              },
              "icon": "links-coming-in",
              "title": "LEGACY_LOGへのバックリンク"
            }
          },
          {
            "id": "626704f55a4a3826",
            "type": "leaf",
            "state": {
              "type": "outgoing-link",
              "state": {
                "file": "docs/LEGACY_LOG.md",
                "linksCollapsed": false,
                "unlinkedCollapsed": true
              },
              "icon": "links-going-out",
              "title": "LEGACY_LOGからのアウトゴーイングリンク"
            }
          },
          {
            "id": "b056d187253b946c",
            "type": "leaf",
            "state": {
              "type": "tag",
              "state": {
                "sortOrder": "frequency",
                "useHierarchy": true,
                "showSearch": false,
                "searchQuery": ""
              },
              "icon": "lucide-tags",
              "title": "タグ"
            }
          },
          {
            "id": "2b573c6499d0d6a3",
            "type": "leaf",
            "state": {
              "type": "all-properties",
              "state": {
                "sortOrder": "frequency",
                "showSearch": false,
                "searchQuery": ""
              },
              "icon": "lucide-archive",
              "title": "すべてのプロパティ"
            }
          },
          {
            "id": "cdb020d41f7c2769",
            "type": "leaf",
            "state": {
              "type": "outline",
              "state": {
                "file": "docs/LEGACY_LOG.md",
                "followCursor": false,
                "showSearch": false,
                "searchQuery": ""
              },
              "icon": "lucide-list",
              "title": "LEGACY_LOGのアウトライン"
            }
          }
        ]
      }
    ],
    "direction": "horizontal",
    "width": 300,
    "collapsed": true
  },
  "left-ribbon": {
    "hiddenItems": {
      "switcher:クイックスイッチャーを開く": false,
      "graph:グラフビューを開く": false,
      "canvas:新規キャンバスを作成": false,
      "daily-notes:今日のデイリーノートを開く": false,
      "templates:テンプレートを挿入": false,
      "command-palette:コマンドパレットを開く": false,
      "bases:新規ベースを作成": false
    }
  },
  "active": "b11e791a2486de83",
  "lastOpenFiles": [
    "SPEC.md.tmp.36008.1775109369811",
    "SPEC.md.tmp.36008.1775101947131",
    "docs/LEGACY_LOG.md",
    "SPEC.md",
    "STRUCTURE.md",
    "docs",
    "ようこそ.md",
    "SPEC.md.tmp.5488.1775097759673"
  ]
}